README.rst
setup.py
django_var_js.egg-info/PKG-INFO
django_var_js.egg-info/SOURCES.txt
django_var_js.egg-info/dependency_links.txt
django_var_js.egg-info/top_level.txt
var_js/__init__.py
var_js/views.py
var_js/dj_var_js/__init__.py
var_js/dj_var_js/urls.py