Metadata-Version: 1.1
Name: django-var-js
Version: 0.1
Summary: Application variables passed from the server to the client.
Home-page: https://github.com/mapeveri/django-var-js
Author: Peveri Martin
Author-email: martinpeveri@gmail.com
License: BSD License
Platform: UNKNOWN
Classifier: Environment :: Web Environment
Classifier: Framework :: Django
Classifier: Intended Audience :: Developers
Classifier: License :: OSI Approved :: BSD License
Classifier: Operating System :: OS Independent
Classifier: Programming Language :: Python
Classifier: Programming Language :: Python :: 2.7
Classifier: Topic :: Internet :: WWW/HTTP
Classifier: Topic :: Internet :: WWW/HTTP :: Dynamic Content
